<?xml version="1.0" encoding="UTF-8"?>
<!-- $TexturePacker:SmartUpdate:cfcbcca5182cbefb53455796cd5804fe:c825ff547072212cce4939dbb7642392:52baf8499a83ed544879e9fa2a26923b$ -->
<CommtyExporter version="1.0">
    <Form id="" name="MainCharacter" file="./forms/MainCharacter.png" width="1023" height="1398"
		fSpacing="0" fMargin="0" fWidth="1" fHeight="1" aColor="255" nFrames="?">
		<Frame id="Male_0_Idle0" fPosX="617" fPosY="110" fWidth="47" fHeight="135" xoffset="105" yoffset="323" width="47"/>
		<Frame id="Male_0_Pickup0" fPosX="175" fPosY="1070" fWidth="47" fHeight="136" xoffset="105" yoffset="323" width="47"/>
		<Frame id="Male_0_Pickup1" fPosX="513" fPosY="224" fWidth="53" fHeight="117" xoffset="112" yoffset="342" width="53"/>
		<Frame id="Male_0_Pickup2" fPosX="945" fPosY="945" fWidth="64" fHeight="79" xoffset="109" yoffset="380" width="64"/>
		<Frame id="Male_0_Pickup3" fPosX="568" fPosY="836" fWidth="63" fHeight="77" xoffset="109" yoffset="382" width="63"/>
		<Frame id="Male_0_Pickup4" fPosX="936" fPosY="1102" fWidth="63" fHeight="80" xoffset="109" yoffset="379" width="63"/>
		<Frame id="Male_0_Pickup5" fPosX="419" fPosY="1294" fWidth="58" fHeight="103" xoffset="113" yoffset="356" width="58"/>
		<Frame id="Male_0_Pickup6" fPosX="475" fPosY="616" fWidth="50" fHeight="122" xoffset="112" yoffset="337" width="50"/>
		<Frame id="Male_0_Pickup7" fPosX="527" fPosY="615" fWidth="46" fHeight="130" xoffset="106" yoffset="329" width="46"/>
		<Frame id="Male_0_Pickup8" fPosX="386" fPosY="480" fWidth="53" fHeight="134" xoffset="99" yoffset="325" width="53"/>
		<Frame id="Male_0_Pickup9" fPosX="224" fPosY="1070" fWidth="54" fHeight="136" xoffset="97" yoffset="323" width="54"/>
		<Frame id="Male_0_Run0" fPosX="83" fPosY="658" fWidth="61" fHeight="134" xoffset="97" yoffset="325" width="61"/>
		<Frame id="Male_0_Run1" fPosX="1" fPosY="524" fWidth="79" fHeight="137" xoffset="83" yoffset="316" width="79"/>
		<Frame id="Male_0_Run2" fPosX="1" fPosY="934" fWidth="85" fHeight="130" xoffset="79" yoffset="313" width="85"/>
		<Frame id="Male_0_Run3" fPosX="652" fPosY="611" fWidth="72" fHeight="120" xoffset="91" yoffset="321" width="72"/>
		<Frame id="Male_0_Run4" fPosX="88" fPosY="943" fWidth="66" fHeight="125" xoffset="101" yoffset="329" width="66"/>
		<Frame id="Male_0_Run5" fPosX="79" fPosY="382" fWidth="64" fHeight="137" xoffset="104" yoffset="322" width="64"/>
		<Frame id="Male_0_Run6" fPosX="1" fPosY="382" fWidth="76" fHeight="140" xoffset="91" yoffset="313" width="76"/>
		<Frame id="Male_0_Run7" fPosX="1" fPosY="1066" fWidth="81" fHeight="130" xoffset="84" yoffset="314" width="81"/>
		<Frame id="Male_0_Run8" fPosX="107" fPosY="121" fWidth="68" fHeight="116" xoffset="96" yoffset="321" width="68"/>
		<Frame id="Male_0_Run9" fPosX="733" fPosY="334" fWidth="58" fHeight="120" xoffset="105" yoffset="330" width="58"/>
		<Frame id="Male_1_Idle0" fPosX="205" fPosY="930" fWidth="28" fHeight="138" xoffset="115" yoffset="324" width="28"/>
		<Frame id="Male_1_Pickup0" fPosX="323" fPosY="233" fWidth="28" fHeight="138" xoffset="115" yoffset="324" width="28"/>
		<Frame id="Male_1_Pickup1" fPosX="611" fPosY="1135" fWidth="66" fHeight="107" xoffset="104" yoffset="354" width="66"/>
		<Frame id="Male_1_Pickup2" fPosX="862" fPosY="937" fWidth="81" fHeight="76" xoffset="91" yoffset="386" width="81"/>
		<Frame id="Male_1_Pickup3" fPosX="929" fPosY="1026" fWidth="80" fHeight="74" xoffset="92" yoffset="388" width="80"/>
		<Frame id="Male_1_Pickup4" fPosX="282" fPosY="1320" fWidth="79" fHeight="77" xoffset="94" yoffset="385" width="79"/>
		<Frame id="Male_1_Pickup5" fPosX="731" fPosY="237" fWidth="76" fHeight="95" xoffset="95" yoffset="367" width="76"/>
		<Frame id="Male_1_Pickup6" fPosX="874" fPosY="334" fWidth="65" fHeight="116" xoffset="95" yoffset="346" width="65"/>
		<Frame id="Male_1_Pickup7" fPosX="347" fPosY="1045" fWidth="50" fHeight="129" xoffset="101" yoffset="333" width="50"/>
		<Frame id="Male_1_Pickup8" fPosX="922" fPosY="124" fWidth="39" fHeight="135" xoffset="105" yoffset="327" width="39"/>
		<Frame id="Male_1_Pickup9" fPosX="201" fPosY="389" fWidth="30" fHeight="138" xoffset="112" yoffset="324" width="30"/>
		<Frame id="Male_1_Run0" fPosX="130" fPosY="1208" fWidth="76" fHeight="115" xoffset="94" yoffset="334" width="76"/>
		<Frame id="Male_1_Run1" fPosX="109" fPosY="1" fWidth="106" fHeight="113" xoffset="71" yoffset="325" width="106"/>
		<Frame id="Male_1_Run2" fPosX="217" fPosY="1" fWidth="113" fHeight="104" xoffset="66" yoffset="322" width="113"/>
		<Frame id="Male_1_Run3" fPosX="773" fPosY="1" fWidth="96" fHeight="121" xoffset="82" yoffset="330" width="96"/>
		<Frame id="Male_1_Run4" fPosX="208" fPosY="1208" fWidth="72" fHeight="117" xoffset="97" yoffset="338" width="72"/>
		<Frame id="Male_1_Run5" fPosX="253" fPosY="107" fWidth="78" fHeight="124" xoffset="96" yoffset="330" width="78"/>
		<Frame id="Male_1_Run6" fPosX="1" fPosY="121" fWidth="104" fHeight="116" xoffset="72" yoffset="322" width="104"/>
		<Frame id="Male_1_Run7" fPosX="447" fPosY="1" fWidth="108" fHeight="104" xoffset="65" yoffset="322" width="108"/>
		<Frame id="Male_1_Run8" fPosX="430" fPosY="107" fWidth="91" fHeight="115" xoffset="81" yoffset="330" width="91"/>
		<Frame id="Male_1_Run9" fPosX="869" fPosY="452" fWidth="70" fHeight="110" xoffset="95" yoffset="339" width="70"/>
		<Frame id="Male_2_Idle0" fPosX="233" fPosY="382" fWidth="49" fHeight="137" xoffset="104" yoffset="325" width="49"/>
		<Frame id="Male_2_Pickup0" fPosX="284" fPosY="376" fWidth="49" fHeight="137" xoffset="104" yoffset="325" width="49"/>
		<Frame id="Male_2_Pickup1" fPosX="941" fPosY="396" fWidth="81" fHeight="98" xoffset="85" yoffset="363" width="81"/>
		<Frame id="Male_2_Pickup2" fPosX="475" fPosY="747" fWidth="94" fHeight="75" xoffset="74" yoffset="388" width="94"/>
		<Frame id="Male_2_Pickup3" fPosX="814" fPosY="763" fWidth="95" fHeight="71" xoffset="73" yoffset="391" width="95"/>
		<Frame id="Male_2_Pickup4" fPosX="911" fPosY="769" fWidth="94" fHeight="74" xoffset="74" yoffset="388" width="94"/>
		<Frame id="Male_2_Pickup5" fPosX="652" fPosY="733" fWidth="92" fHeight="91" xoffset="76" yoffset="371" width="92"/>
		<Frame id="Male_2_Pickup6" fPosX="793" fPosY="334" fWidth="79" fHeight="110" xoffset="81" yoffset="352" width="79"/>
		<Frame id="Male_2_Pickup7" fPosX="469" fPosY="915" fWidth="61" fHeight="126" xoffset="91" yoffset="336" width="61"/>
		<Frame id="Male_2_Pickup8" fPosX="429" fPosY="344" fWidth="51" fHeight="134" xoffset="98" yoffset="328" width="51"/>
		<Frame id="Male_2_Pickup9" fPosX="156" fPosY="930" fWidth="47" fHeight="138" xoffset="101" yoffset="324" width="47"/>
		<Frame id="Male_2_Run0" fPosX="679" fPosY="1242" fWidth="63" fHeight="102" xoffset="102" yoffset="343" width="63"/>
		<Frame id="Male_2_Run1" fPosX="395" fPosY="735" fWidth="78" fHeight="89" xoffset="90" yoffset="334" width="78"/>
		<Frame id="Male_2_Run2" fPosX="835" fPosY="124" fWidth="85" fHeight="104" xoffset="84" yoffset="331" width="85"/>
		<Frame id="Male_2_Run3" fPosX="177" fPosY="116" fWidth="74" fHeight="121" xoffset="96" yoffset="340" width="74"/>
		<Frame id="Male_2_Run4" fPosX="549" fPosY="1274" fWidth="64" fHeight="110" xoffset="106" yoffset="348" width="64"/>
		<Frame id="Male_2_Run5" fPosX="615" fPosY="1244" fWidth="62" fHeight="107" xoffset="100" yoffset="341" width="62"/>
		<Frame id="Male_2_Run6" fPosX="868" fPosY="845" fWidth="80" fHeight="90" xoffset="83" yoffset="332" width="80"/>
		<Frame id="Male_2_Run7" fPosX="744" fPosY="124" fWidth="89" fHeight="107" xoffset="76" yoffset="332" width="89"/>
		<Frame id="Male_2_Run8" fPosX="575" fPosY="611" fWidth="75" fHeight="119" xoffset="89" yoffset="339" width="75"/>
		<Frame id="Male_2_Run9" fPosX="656" fPosY="911" fWidth="66" fHeight="107" xoffset="98" yoffset="348" width="66"/>
		<Frame id="Male_3_Idle0" fPosX="534" fPosY="343" fWidth="59" fHeight="132" xoffset="99" yoffset="325" width="59"/>
		<Frame id="Male_3_Pickup0" fPosX="276" fPosY="797" fWidth="59" fHeight="131" xoffset="99" yoffset="325" width="59"/>
		<Frame id="Male_3_Pickup1" fPosX="798" fPosY="1128" fWidth="71" fHeight="99" xoffset="87" yoffset="363" width="71"/>
		<Frame id="Male_3_Pickup2" fPosX="787" fPosY="933" fWidth="73" fHeight="85" xoffset="86" yoffset="379" width="73"/>
		<Frame id="Male_3_Pickup3" fPosX="575" fPosY="732" fWidth="75" fHeight="83" xoffset="84" yoffset="381" width="75"/>
		<Frame id="Male_3_Pickup4" fPosX="841" fPosY="676" fWidth="76" fHeight="85" xoffset="83" yoffset="379" width="76"/>
		<Frame id="Male_3_Pickup5" fPosX="810" fPosY="1229" fWidth="75" fHeight="99" xoffset="84" yoffset="365" width="75"/>
		<Frame id="Male_3_Pickup6" fPosX="479" fPosY="1285" fWidth="68" fHeight="112" xoffset="90" yoffset="349" width="68"/>
		<Frame id="Male_3_Pickup7" fPosX="145" fPosY="535" fWidth="60" fHeight="121" xoffset="98" yoffset="336" width="60"/>
		<Frame id="Male_3_Pickup8" fPosX="276" fPosY="930" fWidth="60" fHeight="129" xoffset="101" yoffset="328" width="60"/>
		<Frame id="Male_3_Pickup9" fPosX="547" fPosY="477" fWidth="60" fHeight="132" xoffset="100" yoffset="325" width="60"/>
		<Frame id="Male_3_Run0" fPosX="806" fPosY="1020" fWidth="55" fHeight="98" xoffset="102" yoffset="347" width="55"/>
		<Frame id="Male_3_Run1" fPosX="363" fPosY="1315" fWidth="54" fHeight="82" xoffset="101" yoffset="337" width="54"/>
		<Frame id="Male_3_Run2" fPosX="742" fPosY="1129" fWidth="54" fHeight="103" xoffset="100" yoffset="335" width="54"/>
		<Frame id="Male_3_Run3" fPosX="735" fPosY="456" fWidth="56" fHeight="120" xoffset="99" yoffset="345" width="56"/>
		<Frame id="Male_3_Run4" fPosX="745" fPosY="1020" fWidth="59" fHeight="106" xoffset="99" yoffset="353" width="59"/>
		<Frame id="Male_3_Run5" fPosX="950" fPosY="845" fWidth="57" fHeight="98" xoffset="99" yoffset="346" width="57"/>
		<Frame id="Male_3_Run6" fPosX="887" fPosY="1312" fWidth="58" fHeight="85" xoffset="100" yoffset="338" width="58"/>
		<Frame id="Male_3_Run7" fPosX="683" fPosY="1020" fWidth="60" fHeight="107" xoffset="99" yoffset="338" width="60"/>
		<Frame id="Male_3_Run8" fPosX="532" fPosY="915" fWidth="62" fHeight="121" xoffset="97" yoffset="344" width="62"/>
		<Frame id="Male_3_Run9" fPosX="679" fPosY="1135" fWidth="61" fHeight="105" xoffset="97" yoffset="353" width="61"/>
		<Frame id="Male_4_Idle0" fPosX="207" fPosY="529" fWidth="47" fHeight="136" xoffset="104" yoffset="325" width="47"/>
		<Frame id="Male_4_Pickup0" fPosX="346" fPosY="649" fWidth="47" fHeight="135" xoffset="104" yoffset="325" width="47"/>
		<Frame id="Male_4_Pickup1" fPosX="786" fPosY="594" fWidth="53" fHeight="110" xoffset="91" yoffset="357" width="53"/>
		<Frame id="Male_4_Pickup2" fPosX="863" fPosY="1015" fWidth="64" fHeight="98" xoffset="83" yoffset="371" width="64"/>
		<Frame id="Male_4_Pickup3" fPosX="887" fPosY="1214" fWidth="63" fHeight="96" xoffset="84" yoffset="373" width="63"/>
		<Frame id="Male_4_Pickup4" fPosX="871" fPosY="1115" fWidth="63" fHeight="97" xoffset="84" yoffset="372" width="63"/>
		<Frame id="Male_4_Pickup5" fPosX="726" fPosY="594" fWidth="58" fHeight="112" xoffset="85" yoffset="357" width="58"/>
		<Frame id="Male_4_Pickup6" fPosX="345" fPosY="1191" fWidth="50" fHeight="122" xoffset="94" yoffset="343" width="50"/>
		<Frame id="Male_4_Pickup7" fPosX="82" fPosY="1198" fWidth="46" fHeight="128" xoffset="104" yoffset="332" width="46"/>
		<Frame id="Male_4_Pickup8" fPosX="441" fPosY="480" fWidth="53" fHeight="134" xoffset="104" yoffset="326" width="53"/>
		<Frame id="Male_4_Pickup9" fPosX="207" fPosY="667" fWidth="54" fHeight="136" xoffset="105" yoffset="324" width="54"/>
		<Frame id="Male_4_Run0" fPosX="724" fPosY="911" fWidth="61" fHeight="107" xoffset="98" yoffset="342" width="61"/>
		<Frame id="Male_4_Run1" fPosX="650" fPosY="247" fWidth="79" fHeight="94" xoffset="94" yoffset="332" width="79"/>
		<Frame id="Male_4_Run2" fPosX="835" fPosY="230" fWidth="85" fHeight="102" xoffset="92" yoffset="330" width="85"/>
		<Frame id="Male_4_Run3" fPosX="659" fPosY="343" fWidth="72" fHeight="118" xoffset="93" yoffset="341" width="72"/>
		<Frame id="Male_4_Run4" fPosX="746" fPosY="708" fWidth="66" fHeight="108" xoffset="89" yoffset="348" width="66"/>
		<Frame id="Male_4_Run5" fPosX="744" fPosY="1234" fWidth="64" fHeight="102" xoffset="88" yoffset="343" width="64"/>
		<Frame id="Male_4_Run6" fPosX="491" fPosY="824" fWidth="75" fHeight="89" xoffset="90" yoffset="335" width="75"/>
		<Frame id="Male_4_Run7" fPosX="941" fPosY="286" fWidth="81" fHeight="108" xoffset="91" yoffset="334" width="81"/>
		<Frame id="Male_4_Run8" fPosX="207" fPosY="805" fWidth="67" fHeight="122" xoffset="92" yoffset="340" width="67"/>
		<Frame id="Male_4_Run9" fPosX="596" fPosY="915" fWidth="58" fHeight="108" xoffset="93" yoffset="350" width="58"/>
		<Frame id="Male_5_Idle0" fPosX="256" fPosY="521" fWidth="28" fHeight="136" xoffset="113" yoffset="324" width="28"/>
		<Frame id="Male_5_Pickup0" fPosX="263" fPosY="659" fWidth="28" fHeight="136" xoffset="113" yoffset="324" width="28"/>
		<Frame id="Male_5_Pickup1" fPosX="397" fPosY="1176" fWidth="66" fHeight="116" xoffset="86" yoffset="347" width="66"/>
		<Frame id="Male_5_Pickup2" fPosX="941" fPosY="496" fWidth="81" fHeight="96" xoffset="84" yoffset="367" width="81"/>
		<Frame id="Male_5_Pickup3" fPosX="568" fPosY="247" fWidth="80" fHeight="94" xoffset="84" yoffset="370" width="80"/>
		<Frame id="Male_5_Pickup4" fPosX="787" fPosY="836" fWidth="79" fHeight="95" xoffset="83" yoffset="368" width="79"/>
		<Frame id="Male_5_Pickup5" fPosX="841" fPosY="564" fWidth="76" fHeight="110" xoffset="85" yoffset="354" width="76"/>
		<Frame id="Male_5_Pickup6" fPosX="280" fPosY="1061" fWidth="65" fHeight="128" xoffset="96" yoffset="334" width="65"/>
		<Frame id="Male_5_Pickup7" fPosX="482" fPosY="343" fWidth="50" fHeight="134" xoffset="105" yoffset="326" width="50"/>
		<Frame id="Male_5_Pickup8" fPosX="235" fPosY="929" fWidth="39" fHeight="136" xoffset="112" yoffset="324" width="39"/>
		<Frame id="Male_5_Pickup9" fPosX="335" fPosY="373" fWidth="30" fHeight="136" xoffset="114" yoffset="324" width="30"/>
		<Frame id="Male_5_Run0" fPosX="666" fPosY="111" fWidth="76" fHeight="124" xoffset="86" yoffset="332" width="76"/>
		<Frame id="Male_5_Run1" fPosX="1" fPosY="1" fWidth="106" fHeight="118" xoffset="79" yoffset="323" width="106"/>
		<Frame id="Male_5_Run2" fPosX="332" fPosY="1" fWidth="113" fHeight="103" xoffset="77" yoffset="321" width="113"/>
		<Frame id="Male_5_Run3" fPosX="333" fPosY="106" fWidth="95" fHeight="114" xoffset="79" yoffset="331" width="95"/>
		<Frame id="Male_5_Run4" fPosX="537" fPosY="1159" fWidth="72" fHeight="113" xoffset="87" yoffset="338" width="72"/>
		<Frame id="Male_5_Run5" fPosX="395" fPosY="616" fWidth="78" fHeight="117" xoffset="82" yoffset="333" width="78"/>
		<Frame id="Male_5_Run6" fPosX="667" fPosY="1" fWidth="104" fHeight="108" xoffset="80" yoffset="326" width="104"/>
		<Frame id="Male_5_Run7" fPosX="557" fPosY="1" fWidth="108" fHeight="107" xoffset="83" yoffset="325" width="108"/>
		<Frame id="Male_5_Run8" fPosX="871" fPosY="1" fWidth="91" fHeight="121" xoffset="84" yoffset="331" width="91"/>
		<Frame id="Male_5_Run9" fPosX="465" fPosY="1168" fWidth="70" fHeight="115" xoffset="91" yoffset="341" width="70"/>
		<Frame id="Male_6_Idle0" fPosX="496" fPosY="479" fWidth="49" fHeight="134" xoffset="103" yoffset="323" width="49"/>
		<Frame id="Male_6_Pickup0" fPosX="286" fPosY="515" fWidth="49" fHeight="136" xoffset="103" yoffset="323" width="49"/>
		<Frame id="Male_6_Pickup1" fPosX="430" fPosY="224" fWidth="81" fHeight="117" xoffset="90" yoffset="338" width="81"/>
		<Frame id="Male_6_Pickup2" fPosX="395" fPosY="826" fWidth="94" fHeight="87" xoffset="88" yoffset="368" width="94"/>
		<Frame id="Male_6_Pickup3" fPosX="919" fPosY="594" fWidth="95" fHeight="84" xoffset="88" yoffset="371" width="95"/>
		<Frame id="Male_6_Pickup4" fPosX="919" fPosY="680" fWidth="94" fHeight="87" xoffset="88" yoffset="368" width="94"/>
		<Frame id="Male_6_Pickup5" fPosX="523" fPosY="110" fWidth="92" fHeight="109" xoffset="88" yoffset="346" width="92"/>
		<Frame id="Male_6_Pickup6" fPosX="1" fPosY="1198" fWidth="79" fHeight="128" xoffset="96" yoffset="329" width="79"/>
		<Frame id="Male_6_Pickup7" fPosX="82" fPosY="521" fWidth="61" fHeight="135" xoffset="104" yoffset="324" width="61"/>
		<Frame id="Male_6_Pickup8" fPosX="293" fPosY="653" fWidth="51" fHeight="136" xoffset="107" yoffset="323" width="51"/>
		<Frame id="Male_6_Pickup9" fPosX="337" fPosY="511" fWidth="47" fHeight="136" xoffset="108" yoffset="323" width="47"/>
		<Frame id="Male_6_Run0" fPosX="81" fPosY="239" fWidth="63" fHeight="141" xoffset="91" yoffset="324" width="63"/>
		<Frame id="Male_6_Run1" fPosX="1" fPosY="239" fWidth="78" fHeight="141" xoffset="88" yoffset="314" width="78"/>
		<Frame id="Male_6_Run2" fPosX="1" fPosY="800" fWidth="85" fHeight="132" xoffset="87" yoffset="312" width="85"/>
		<Frame id="Male_6_Run3" fPosX="793" fPosY="446" fWidth="74" fHeight="115" xoffset="86" yoffset="322" width="74"/>
		<Frame id="Male_6_Run4" fPosX="467" fPosY="1043" fWidth="64" fHeight="121" xoffset="86" yoffset="329" width="64"/>
		<Frame id="Male_6_Run5" fPosX="595" fPosY="343" fWidth="62" fHeight="132" xoffset="94" yoffset="324" width="62"/>
		<Frame id="Male_6_Run6" fPosX="1" fPosY="663" fWidth="80" fHeight="135" xoffset="93" yoffset="316" width="80"/>
		<Frame id="Male_6_Run7" fPosX="84" fPosY="1070" fWidth="89" fHeight="125" xoffset="91" yoffset="316" width="89"/>
		<Frame id="Male_6_Run8" fPosX="353" fPosY="222" fWidth="75" fHeight="120" xoffset="92" yoffset="322" width="75"/>
		<Frame id="Male_6_Run9" fPosX="399" fPosY="1042" fWidth="66" fHeight="124" xoffset="92" yoffset="332" width="66"/>
		<Frame id="Male_7_Idle0" fPosX="963" fPosY="151" fWidth="59" fHeight="133" xoffset="98" yoffset="322" width="59"/>
		<Frame id="Male_7_Pickup0" fPosX="146" fPosY="658" fWidth="59" fHeight="134" xoffset="98" yoffset="322" width="59"/>
		<Frame id="Male_7_Pickup1" fPosX="533" fPosY="1038" fWidth="71" fHeight="119" xoffset="98" yoffset="336" width="71"/>
		<Frame id="Male_7_Pickup2" fPosX="711" fPosY="826" fWidth="73" fHeight="83" xoffset="97" yoffset="372" width="73"/>
		<Frame id="Male_7_Pickup3" fPosX="947" fPosY="1312" fWidth="75" fHeight="79" xoffset="97" yoffset="376" width="75"/>
		<Frame id="Male_7_Pickup4" fPosX="633" fPosY="826" fWidth="76" fHeight="83" xoffset="97" yoffset="371" width="76"/>
		<Frame id="Male_7_Pickup5" fPosX="606" fPosY="1025" fWidth="75" fHeight="108" xoffset="97" yoffset="347" width="75"/>
		<Frame id="Male_7_Pickup6" fPosX="399" fPosY="915" fWidth="68" fHeight="125" xoffset="98" yoffset="330" width="68"/>
		<Frame id="Male_7_Pickup7" fPosX="609" fPosY="477" fWidth="60" fHeight="132" xoffset="98" yoffset="324" width="60"/>
		<Frame id="Male_7_Pickup8" fPosX="145" fPosY="794" fWidth="60" fHeight="134" xoffset="95" yoffset="322" width="60"/>
		<Frame id="Male_7_Pickup9" fPosX="367" fPosY="344" fWidth="60" fHeight="134" xoffset="96" yoffset="322" width="60"/>
		<Frame id="Male_7_Run0" fPosX="88" fPosY="794" fWidth="55" fHeight="147" xoffset="99" yoffset="320" width="55"/>
		<Frame id="Male_7_Run1" fPosX="146" fPosY="239" fWidth="54" fHeight="148" xoffset="101" yoffset="311" width="54"/>
		<Frame id="Male_7_Run2" fPosX="145" fPosY="389" fWidth="54" fHeight="144" xoffset="102" yoffset="308" width="54"/>
		<Frame id="Male_7_Run3" fPosX="337" fPosY="791" fWidth="56" fHeight="122" xoffset="101" yoffset="317" width="56"/>
		<Frame id="Male_7_Run4" fPosX="338" fPosY="915" fWidth="59" fHeight="128" xoffset="98" yoffset="325" width="59"/>
		<Frame id="Male_7_Run5" fPosX="202" fPosY="239" fWidth="57" fHeight="141" xoffset="100" yoffset="318" width="57"/>
		<Frame id="Male_7_Run6" fPosX="964" fPosY="1" fWidth="58" fHeight="148" xoffset="98" yoffset="310" width="58"/>
		<Frame id="Male_7_Run7" fPosX="261" fPosY="233" fWidth="60" fHeight="141" xoffset="97" yoffset="310" width="60"/>
		<Frame id="Male_7_Run8" fPosX="671" fPosY="463" fWidth="62" fHeight="119" xoffset="97" yoffset="317" width="62"/>
		<Frame id="Male_7_Run9" fPosX="282" fPosY="1191" fWidth="61" fHeight="127" xoffset="98" yoffset="327" width="61"/>
    </Form>
</CommtyExporter>
